<?xml version="1.0" encoding="UTF-8"?>
<language xmlns="http://www.woltlab.com" xmlns:xsi="http://www.w3.org/2001/XMLSchema-instance" xsi:schemaLocation="http://www.woltlab.com http://www.woltlab.com/XSD/maelstrom/language.xsd" languagecode="en">
	<category name="wcf.acp.group">
		<item name="wcf.acp.group.option.admin.content.label.canAddLabel"><![CDATA[Can add labels]]></item>
		<item name="wcf.acp.group.option.admin.content.label.canAddLabelGroup"><![CDATA[Can add label groups]]></item>
		<item name="wcf.acp.group.option.admin.content.label.canDeleteLabel"><![CDATA[Can delete labels]]></item>
		<item name="wcf.acp.group.option.admin.content.label.canDeleteLabelGroup"><![CDATA[Can delete label groups]]></item>
		<item name="wcf.acp.group.option.admin.content.label.canEditLabel"><![CDATA[Can edit labels]]></item>
		<item name="wcf.acp.group.option.admin.content.label.canEditLabelGroup"><![CDATA[Can edit label groups]]></item>
		<item name="wcf.acp.group.option.category.admin.content.label"><![CDATA[Labels]]></item>
	</category>
	
	<category name="wcf.acp.label">
		<item name="wcf.acp.label.add"><![CDATA[Add Label]]></item>
		<item name="wcf.acp.label.cssClassName"><![CDATA[CSS Class Name]]></item>
		<item name="wcf.acp.label.data"><![CDATA[Label Data]]></item>
		<item name="wcf.acp.label.defaultValue"><![CDATA[Label]]></item>
		<item name="wcf.acp.label.error.noGroups"><![CDATA[Please <a href="{link controller='LabelGroupAdd'}{/link}">add a label group</a> prior to creating labels.]]></item>
		<item name="wcf.acp.label.group"><![CDATA[Label Group]]></item>
		<item name="wcf.acp.label.group.add"><![CDATA[Add Label Group]]></item>
		<item name="wcf.acp.label.group.data"><![CDATA[Label Group Data]]></item>
		<item name="wcf.acp.label.group.groupName"><![CDATA[Title]]></item>
		<item name="wcf.acp.label.group.list"><![CDATA[Label Groups]]></item>
		<item name="wcf.acp.label.group.noneAvailable"><![CDATA[There are no label groups yet.]]></item>
		<item name="wcf.acp.label.label"><![CDATA[Label]]></item>
		<item name="wcf.acp.label.list"><![CDATA[Labels]]></item>
		<item name="wcf.acp.label.noneAvailable"><![CDATA[There are no labels yet.]]></item>
	</category>
	
	<category name="wcf.acp.menu">
		<item name="wcf.acp.menu.link.label"><![CDATA[Labels]]></item>
		<item name="wcf.acp.menu.link.label.list"><![CDATA[List Labels]]></item>
		<item name="wcf.acp.menu.link.label.add"><![CDATA[Add Label]]></item>
		<item name="wcf.acp.menu.link.label.group.list"><![CDATA[List Label Groups]]></item>
		<item name="wcf.acp.menu.link.label.group.add"><![CDATA[Add Label Group]]></item>
	</category>
	
	<category name="wcf.label">
		<item name="wcf.label.none"><![CDATA[No Selection]]></item>
		<item name="wcf.label.label"><![CDATA[Label]]></item>
		<item name="wcf.label.labels"><![CDATA[Labels]]></item>
	</category>
</language>